teomim/__init__.py
teomim/io.py
teomim/teomim.py
teomim/viz.py
teomim/assets/adrd_5K_01.pkl.gz
teomim-0.0.166.dist-info/LICENSE
teomim-0.0.166.dist-info/METADATA
teomim-0.0.166.dist-info/WHEEL
teomim-0.0.166.dist-info/top_level.txt
teomim-0.0.166.dist-info/RECORD
