Metadata-Version: 2.1
Name: teomim
Version: 0.0.166
Summary: Digital twin for generating and analyzing medical histories with deep comorbidity structures
Home-page: https://github.com/zeroknowledgediscovery/teomim
Download-URL: https://github.com/zeroknowledgediscovery/teomim/archive/0.0.166.tar.gz
Author: paraknowledge corp
Author-email: research@paraknowledge.ai
License: LICENSE
Keywords: machine learning,statistics
Classifier: Development Status :: 4 - Beta
Classifier: Intended Audience :: Developers
Classifier: Intended Audience :: Science/Research
Classifier: Topic :: Scientific/Engineering :: Information Analysis
Classifier: Topic :: Software Development :: Libraries
Classifier: License :: OSI Approved :: MIT License
Classifier: Programming Language :: Python :: 3.7
Requires-Python: >=3.7
License-File: LICENSE
Requires-Dist: scikit-learn
Requires-Dist: scipy
Requires-Dist: numpy
Requires-Dist: pandas
Requires-Dist: quasinet (>=0.1.63)
